headercount/__init__.py
headercount/__main__.py
headercount/files.py
headercount/includes.py
headercount-1.0.1.dist-info/METADATA
headercount-1.0.1.dist-info/WHEEL
headercount-1.0.1.dist-info/entry_points.txt
headercount-1.0.1.dist-info/top_level.txt
headercount-1.0.1.dist-info/zip-safe
headercount-1.0.1.dist-info/RECORD
