Metadata-Version: 2.4
Name: headercount
Version: 1.0.1
Summary: Count directly and indirectly included headers in a C/C++ project
Author-email: Broken Pen <pnuuy@pm.me>
License-Expression: Apache-2.0
Project-URL: gitlab, https://git.sr.ht/~brokenpen/headercount
Keywords: header,include,c,c++,include
Classifier: Development Status :: 5 - Production/Stable
Classifier: Environment :: Console
Classifier: Intended Audience :: Developers
Classifier: Topic :: Software Development :: Debuggers
Classifier: Natural Language :: English
Classifier: Operating System :: OS Independent
Classifier: Programming Language :: Python :: 3.4
Classifier: Programming Language :: Python :: 3.4
Classifier: Programming Language :: Python :: 3.4
Classifier: Programming Language :: Python :: 3.5
Classifier: Programming Language :: Python :: 3.6
Classifier: Programming Language :: Python :: 3.7
Classifier: Programming Language :: Python :: 3 :: Only
Requires-Python: >=3.4
Requires-Dist: importlib-metadata>=4.6; python_version < "3.8"
Requires-Dist: typing-extensions>=4.6; python_version < "3.12"
Provides-Extra: dev
Requires-Dist: pytest>=8; extra == "dev"
Requires-Dist: pytest-cov>=5; extra == "dev"
